gridcentric_python_novaclient_ext
