Metadata-Version: 1.0
Name: gridcentric-python-novaclient-ext
Version: 1.2.1533
Summary: GridCentric extension for OS novaclient.
Home-page: http://www.gridcentric.com/
Author: GridCentric
Author-email: support@gridcentric.com
License: UNKNOWN
Platform: UNKNOWN
